LICENSE
MANIFEST.in
setup.py
passwords/__init__.py
passwords/pbkdf2.py
passwords.egg-info/PKG-INFO
passwords.egg-info/SOURCES.txt
passwords.egg-info/dependency_links.txt
passwords.egg-info/top_level.txt