Metadata-Version: 1.0
Name: passwords
Version: 0.2.0
Summary: Passwords for everyone.
Home-page: http://github.com/kudos/passwords
Author: Jonathan Cremin
Author-email: jonathan@crem.in
License: Copyright (c) 2012 Jonathan Cremin.
